menucraft/__init__.py
menucraft/menu.py
menucraft-0.0.1.dist-info/LICENSE
menucraft-0.0.1.dist-info/METADATA
menucraft-0.0.1.dist-info/WHEEL
menucraft-0.0.1.dist-info/top_level.txt
menucraft-0.0.1.dist-info/RECORD
