Metadata-Version: 2.1
Name: menucraft
Version: 0.0.1
Summary: A simple package for generating menus for cli interactive programs where user input is required.
Author-email: Eduards Abishevs <eduards@abishevs.dev>
Project-URL: Homepage, https://github.com/Abishevs/MenuCraft
Project-URL: Bug Tracker, https://github.com/Abishevs/MenuCraft/issues
Keywords: Cli,cli-interactive-menu,Menu
Classifier: Programming Language :: Python :: 3
Classifier: License :: OSI Approved :: MIT License
Classifier: Operating System :: OS Independent
Requires-Python: >=3.7
License-File: LICENSE
